suficloud/__init__.py
suficloud/main.py
suficloud-3.0.0.dist-info/METADATA
suficloud-3.0.0.dist-info/WHEEL
suficloud-3.0.0.dist-info/top_level.txt
suficloud-3.0.0.dist-info/RECORD
