Metadata-Version: 2.4
Name: suficloud
Version: 3.0.0
Summary: Secure Cloud Storage Service
Author: Sufiyan
Author-email: abcdxyz@email.com
Classifier: Programming Language :: Python :: 3
Classifier: License :: OSI Approved :: MIT License
Classifier: Operating System :: Android
Requires-Python: >=3.6
Requires-Dist: requests
Dynamic: author
Dynamic: author-email
Dynamic: classifier
Dynamic: description
Dynamic: description-content-type
Dynamic: requires-dist
Dynamic: requires-python
Dynamic: summary
